jaxtorch/__init__.py
jaxtorch/_version.py
jaxtorch/cbor.py
jaxtorch/core.py
jaxtorch/image.py
jaxtorch/init.py
jaxtorch/pt.py
jaxtorch/nn/__init__.py
jaxtorch/nn/functional.py
jaxtorch/nn/image.py
jaxtorch/nn/modules.py
jaxtorch-0.6.0.dist-info/METADATA
jaxtorch-0.6.0.dist-info/WHEEL
jaxtorch-0.6.0.dist-info/licenses/COPYING
jaxtorch-0.6.0.dist-info/RECORD
