Metadata-Version: 2.4
Name: jaxtorch
Version: 0.6.0
Summary: A jax based nn library
Project-URL: Homepage, https://github.com/nshepperd/jaxtorch
Author: Emily Shepperd
License: MIT
License-File: COPYING
Classifier: License :: OSI Approved :: MIT License
Classifier: Programming Language :: Python :: 3
Classifier: Programming Language :: Python :: 3.9
Requires-Dist: jax>=0.4.38
Requires-Dist: numpy
